ns_asphalt9/main.py
ns_asphalt9/core/__init__.py
ns_asphalt9/core/cache.py
ns_asphalt9/core/capture.py
ns_asphalt9/core/consts.py
ns_asphalt9/core/controller.py
ns_asphalt9/core/errors.py
ns_asphalt9/core/event.py
ns_asphalt9/core/globals.py
ns_asphalt9/core/ocr.py
ns_asphalt9/core/page_factory.py
ns_asphalt9/core/pages.py
ns_asphalt9/core/reset_data.py
ns_asphalt9/core/screenshot.py
ns_asphalt9/core/tasks.py
ns_asphalt9/core/test.py
ns_asphalt9/core/actions/__init__.py
ns_asphalt9/core/actions/autocode.py
ns_asphalt9/core/actions/common.py
ns_asphalt9/core/actions/enter_page.py
ns_asphalt9/core/actions/process_race.py
ns_asphalt9/core/actions/select_car.py
ns_asphalt9/core/gui/__init__.py
ns_asphalt9/core/gui/app.py
ns_asphalt9/core/gui/images/console.png
ns_asphalt9/core/gui/images/help.png
ns_asphalt9/core/gui/images/home.png
ns_asphalt9/core/gui/images/logo.png
ns_asphalt9/core/gui/images/record.png
ns_asphalt9/core/gui/images/reward.png
ns_asphalt9/core/gui/images/reward1.png
ns_asphalt9/core/gui/images/reward2.png
ns_asphalt9/core/gui/images/reward3.png
ns_asphalt9/core/gui/images/reward_qrcode.jpeg
ns_asphalt9/core/gui/images/screen.png
ns_asphalt9/core/gui/images/settings.png
ns_asphalt9/core/utils/__init__.py
ns_asphalt9/core/utils/count.py
ns_asphalt9/core/utils/credits.py
ns_asphalt9/core/utils/decorator.py
ns_asphalt9/core/utils/error_process.py
ns_asphalt9/core/utils/lifo_queue.py
ns_asphalt9/core/utils/log.py
ns_asphalt9/core/utils/notify.py
ns_asphalt9/core/utils/online_tracker.py
ns_asphalt9/core/utils/page_stack.py
ns_asphalt9/core/utils/process_record_data.py
ns_asphalt9/core/utils/thread_lifo_queue.py
ns_asphalt9/core/utils/timer.py
ns_asphalt9/core/utils/track_data.py
ns_asphalt9/core/utils/track_navi_data.py
ns_asphalt9/core/utils/track_navi_data_update.py
ns_asphalt9/core/utils/track_navi_data_v2.py
ns_asphalt9/core/utils/track_navi_data_win.py
ns_asphalt9-3.5.1.dist-info/LICENSE
ns_asphalt9-3.5.1.dist-info/METADATA
ns_asphalt9-3.5.1.dist-info/WHEEL
ns_asphalt9-3.5.1.dist-info/entry_points.txt
ns_asphalt9-3.5.1.dist-info/top_level.txt
ns_asphalt9-3.5.1.dist-info/RECORD
