Metadata-Version: 2.1
Name: ns_asphalt9
Version: 3.5.1
Summary: Asphalt 9 daily task handling tool based on NXBT and V4L2.
Home-page: https://pypi.python.org/pypi/ns_asphalt9
Author: codehai
Author-email: wmpksb@gmail.com
License: GNU General Public License v3 (GPLv3)
Project-URL: Code, https://github.com/codehai/ns_asphalt9
Project-URL: Issue tracker, https://github.com/codehai/ns_asphalt9/issues
Platform: any
Classifier: Development Status :: 3 - Alpha
Classifier: Intended Audience :: Developers
Classifier: License :: OSI Approved :: GNU General Public License v3 (GPLv3)
Classifier: Operating System :: OS Independent
Classifier: Programming Language :: Python
Classifier: Programming Language :: Python :: 3.6
Classifier: Programming Language :: Python :: 3.7
Classifier: Programming Language :: Python :: 3.8
Classifier: Topic :: Software Development :: Libraries :: Python Modules
Requires-Python: >=3.6
License-File: LICENSE
Requires-Dist: beautifulsoup4 ==4.11.2
Requires-Dist: customtkinter ==5.2.0
Requires-Dist: nxbt ==0.1.4
Requires-Dist: Pillow ==9.5.0
Requires-Dist: pytesseract ==0.3.10
Requires-Dist: Requests ==2.31.0
Requires-Dist: opencv-python ==4.9.0.80
